src/__init__.py
src/dtween/__init__.py
src/dtween/available/__init__.py
src/dtween/available/available.py
src/dtween/available/constants.py
src/dtween/available/ext.py
src/dtween/digitaltwin/__init__.py
src/dtween/digitaltwin/diagnostics/__init__.py
src/dtween/digitaltwin/diagnostics/algorithm.py
src/dtween/digitaltwin/diagnostics/util.py
src/dtween/digitaltwin/diagnostics/versions/__init__.py
src/dtween/digitaltwin/diagnostics/versions/token_based_replay.py
src/dtween/digitaltwin/digitaltwin/__init__.py
src/dtween/digitaltwin/digitaltwin/util.py
src/dtween/digitaltwin/digitaltwin/evaluation/__init__.py
src/dtween/digitaltwin/digitaltwin/evaluation/factory.py
src/dtween/digitaltwin/digitaltwin/objects/__init__.py
src/dtween/digitaltwin/digitaltwin/objects/factory.py
src/dtween/digitaltwin/digitaltwin/objects/obj.py
src/dtween/digitaltwin/digitaltwin/operation/__init__.py
src/dtween/digitaltwin/digitaltwin/operation/factory.py
src/dtween/digitaltwin/digitaltwin/operation/versions/__init__.py
src/dtween/digitaltwin/digitaltwin/operation/versions/projection.py
src/dtween/digitaltwin/digitaltwin/visualization/__init__.py
src/dtween/digitaltwin/digitaltwin/visualization/visualizer.py
src/dtween/digitaltwin/digitaltwin/visualization/versions/__init__.py
src/dtween/digitaltwin/digitaltwin/visualization/versions/graphviz_based.py
src/dtween/digitaltwin/mvp/__init__.py
src/dtween/digitaltwin/mvp/projection/__init__.py
src/dtween/digitaltwin/mvp/projection/algorithm.py
src/dtween/digitaltwin/mvp/projection/versions/__init__.py
src/dtween/digitaltwin/mvp/projection/versions/activity_occurrence.py
src/dtween/digitaltwin/mvp/projection/versions/classic.py
src/dtween/digitaltwin/mvp/projection/versions/group_size_hist.py
src/dtween/digitaltwin/ocel/__init__.py
src/dtween/digitaltwin/valve/__init__.py
src/dtween/digitaltwin/valve/objects/__init__.py
src/dtween/digitaltwin/valve/objects/factory.py
src/dtween/digitaltwin/valve/objects/obj.py
src/dtween/parsedata/__init__.py
dtween-0.0.4.dist-info/LICENSE
dtween-0.0.4.dist-info/METADATA
dtween-0.0.4.dist-info/WHEEL
dtween-0.0.4.dist-info/top_level.txt
dtween-0.0.4.dist-info/RECORD
